tripplite/__init__.py
tripplite/collectors.py
tripplite/driver.py
tripplite/prometheus.py
tripplite-0.4.0.dist-info/LICENSE
tripplite-0.4.0.dist-info/METADATA
tripplite-0.4.0.dist-info/WHEEL
tripplite-0.4.0.dist-info/entry_points.txt
tripplite-0.4.0.dist-info/top_level.txt
tripplite-0.4.0.dist-info/RECORD
