Metadata-Version: 2.1
Name: tripplite
Version: 0.4.0
Summary: Python driver for TrippLite UPS battery backups.
Home-page: https://github.com/numat/tripplite/
Author: Patrick Fuller
Author-email: pat@numat-tech.com
License: GPLv2
Classifier: License :: OSI Approved :: GNU General Public License v2 (GPLv2)
Classifier: Development Status :: 4 - Beta
Classifier: Natural Language :: English
Classifier: Programming Language :: Python
Classifier: Topic :: Scientific/Engineering :: Human Machine Interfaces
License-File: LICENSE
Requires-Dist: hidapi
Provides-Extra: exporter
Requires-Dist: prometheus-client ; extra == 'exporter'
Provides-Extra: test
Requires-Dist: ruff ; extra == 'test'
